app/__init__.py
app/simplecalculator/__init__.py
app/simplecalculator/src/__init__.py
app/simplecalculator/src/calculator.py
simplecalculator_turing-0.0.6.dist-info/LICENSE.TXT
simplecalculator_turing-0.0.6.dist-info/METADATA
simplecalculator_turing-0.0.6.dist-info/WHEEL
simplecalculator_turing-0.0.6.dist-info/entry_points.txt
simplecalculator_turing-0.0.6.dist-info/top_level.txt
simplecalculator_turing-0.0.6.dist-info/RECORD
