Metadata-Version: 2.1
Name: simplecalculator-turing
Version: 0.0.6
Summary: A simple command-line calculator program that can perform basic arithmetic operations and nth root calculation.
Home-page: https://github.com/TuringCollegeSubmissions/arocas-DWWP.1.5
Author: Armin Rocas
Author-email: armin.rocas@live.com
License: GPL-3.0
Classifier: License :: OSI Approved :: GNU General Public License v3 (GPLv3)
Classifier: Programming Language :: Python :: 3.9
Classifier: Operating System :: OS Independent
Requires-Python: >=3.9
License-File: LICENSE.TXT
